gllib/__init__.py
gllib/attribute.py
gllib/contextmanager.py
gllib/framebuffer.py
gllib/fsquad.py
gllib/gl.py
gllib/matrix.py
gllib/sdl_runner.py
gllib/shader.py
gllib/texture.py
gllib/uniform.py
gllib/util.py
gllib/vao.py
gllib/vbo.py
gllib/vector.py
gllib-0.1.1.dist-info/METADATA
gllib-0.1.1.dist-info/WHEEL
gllib-0.1.1.dist-info/top_level.txt
gllib-0.1.1.dist-info/RECORD
